LICENSE
README.md
setup.py
algo_fun/__init__.py
algo_fun/factorial.py
algo_fun_factorial.egg-info/PKG-INFO
algo_fun_factorial.egg-info/SOURCES.txt
algo_fun_factorial.egg-info/dependency_links.txt
algo_fun_factorial.egg-info/top_level.txt
tests/__init__.py
tests/test_factorial.py