Metadata-Version: 2.1
Name: algo-fun-factorial
Version: 0.1.0
Summary: Give the factorial of a given number
Home-page: https://gitlab.com/ChristopheLagaillarde/algo_fun_factorial
Author: Christophe Lagaillarde
Author-email: chrislag94@gmail.com
License: MIT
License-File: LICENSE
